intelligent_water_droplet/IWD.py
intelligent_water_droplet/__init__.py
intelligent_water_droplet-0.0.3.dist-info/LICENSE.md
intelligent_water_droplet-0.0.3.dist-info/METADATA
intelligent_water_droplet-0.0.3.dist-info/WHEEL
intelligent_water_droplet-0.0.3.dist-info/top_level.txt
intelligent_water_droplet-0.0.3.dist-info/RECORD
