Metadata-Version: 2.1
Name: intelligent-water-droplet
Version: 0.0.3
Summary: A python implementation of the Intelligent Water Droplet, a Swarm based optimization algorithm
Home-page: https://github.com/manupillai308/Intelligent-Water-Droplet
Author: Manu S Pillai
Author-email: manupillai308@gmail.com
License: UNKNOWN
Platform: UNKNOWN
Classifier: Programming Language :: Python :: 3
Classifier: License :: OSI Approved :: MIT License
Classifier: Operating System :: OS Independent
Requires-Dist: numpy
